{"version":"0.1.0","name":"tresaurus","dependencies":{"@emotion/react":{"version":"11.10.5"},"@emotion/styled":{"version":"11.10.5"},"@mui/icons-material":{"version":"5.10.16"},"@mui/material":{"version":"5.10.16"},"@reduxjs/toolkit":{"version":"1.9.1"},"@testing-library/jest-dom":{"version":"5.16.5"},"@testing-library/react":{"version":"13.4.0"},"@testing-library/user-event":{"version":"14.4.3"},"@types/jest":{"version":"27.5.2"},"@types/node":{"version":"17.0.45"},"@types/react-dom":{"version":"18.0.9"},"@types/react":{"version":"18.0.25"},"axios":{"version":"1.2.0"},"localforage":{"version":"1.10.0"},"match-sorter":{"version":"6.3.1"},"notistack":{"version":"2.0.8"},"react-dom":{"version":"18.2.0"},"react-redux":{"version":"8.0.5"},"react-router-dom":{"version":"6.4.4"},"react-scripts":{"version":"5.0.1"},"react":{"version":"18.2.0"},"sort-by":{"version":"1.2.0"},"typescript":{"version":"4.9.3"},"web-vitals":{"version":"2.1.4"}}}